valyte/Logo.png
valyte/__init__.py
valyte/band.py
valyte/band_plot.py
valyte/cli.py
valyte/dos_plot.py
valyte/kpoints.py
valyte/potcar.py
valyte/supercell.py
valyte/valyte_band.png
valyte/valyte_dos.png
valyte/data/__init__.py
valyte/data/bradcrack.json
valyte-0.1.9.dist-info/METADATA
valyte-0.1.9.dist-info/WHEEL
valyte-0.1.9.dist-info/entry_points.txt
valyte-0.1.9.dist-info/top_level.txt
valyte-0.1.9.dist-info/RECORD
