Metadata-Version: 2.1
Name: valyte
Version: 0.1.9
Summary: A comprehensive CLI tool for VASP pre-processing (Supercells, K-points) and post-processing (DOS, Band Structure plotting)
Home-page: https://github.com/nikyadav002/Valyte-Project
Author: Nikhil
Author-email: nikhil@example.com
Classifier: Programming Language :: Python :: 3
Classifier: License :: OSI Approved :: MIT License
Classifier: Operating System :: OS Independent
Requires-Python: >=3.6
Requires-Dist: numpy
Requires-Dist: matplotlib
Requires-Dist: pymatgen
Requires-Dist: scipy
Requires-Dist: click
Requires-Dist: seekpath
